enochecker_async/__init__.py
enochecker_async/enochecker.py
enochecker_async-0.5.0.dist-info/LICENSE
enochecker_async-0.5.0.dist-info/METADATA
enochecker_async-0.5.0.dist-info/WHEEL
enochecker_async-0.5.0.dist-info/top_level.txt
enochecker_async-0.5.0.dist-info/RECORD
