Metadata-Version: 2.1
Name: enochecker-async
Version: 0.5.0
Summary: Library to build async checker scripts for the EnoEngine A/D CTF Framework in Python
Home-page: https://github.com/enowars/enochecker_async
Author: Trolldemorted
Author-email: benediktradtke@gmail.com
License: UNKNOWN
Platform: UNKNOWN
Classifier: Development Status :: 4 - Beta
Classifier: License :: OSI Approved :: MIT License
Classifier: Programming Language :: Python :: 3.7
Classifier: Programming Language :: Python :: 3.8
Classifier: Programming Language :: Python :: 3.9
Requires-Python: >=3.7
Requires-Dist: enochecker-core (==0.9.0)
Requires-Dist: jsons (==1.4.2)
Requires-Dist: motor (==2.4.0)
Requires-Dist: pymongo (==3.11.3)
Requires-Dist: tornado (==6.1)
Requires-Dist: typish (==1.9.2)
